marcelle/__init__.py
marcelle/data_store.py
marcelle/keras_callback.py
marcelle/remote.py
marcelle/uploader.py
marcelle/utils.py
marcelle/writer.py
marcelle-0.0.5.dist-info/LICENSE
marcelle-0.0.5.dist-info/WHEEL
marcelle-0.0.5.dist-info/METADATA
marcelle-0.0.5.dist-info/RECORD
