Metadata-Version: 2.1
Name: marcelle
Version: 0.0.5
Summary: Python package for interacting with Marcelle
Home-page: https://marcelle.dev/
License: MIT
Keywords: Marcelle,Interactive Machine Learning,Tensorflow,Tensorflow.js,Keras,ONNX
Author: Jules Françoise
Author-email: me@julesfrancoise.com
Maintainer: Jules Françoise
Maintainer-email: me@julesfrancoise.com
Requires-Python: >=3.8,<3.10
Classifier: Development Status :: 3 - Alpha
Classifier: License :: OSI Approved :: MIT License
Classifier: Operating System :: OS Independent
Classifier: Programming Language :: Python :: 3
Classifier: Programming Language :: Python :: 3.8
Classifier: Programming Language :: Python :: 3.9
Requires-Dist: filetype (>=1.0.8,<2.0.0)
Requires-Dist: keras2onnx (>=1.7.0,<2.0.0)
Requires-Dist: numpy (>=1.21.4,<2.0.0)
Requires-Dist: requests (>=2.26.0,<3.0.0)
Requires-Dist: tensorflow (>=2.7.0,<3.0.0)
Requires-Dist: tensorflowjs (>=3.11.0,<4.0.0)
Requires-Dist: tqdm (>=4.62.3,<5.0.0)
Project-URL: Documentation, https://marcelle.dev/api/python.html
Project-URL: Repository, https://github.com/marcellejs/python/
